{"sections":{"cd3dffdd-4f31-48e4-ac68-b329003b6168":{"type":"dynamic-image-with-text","custom_css":[],"settings":{"section_heading":"","image":"shopify:\/\/shop_images\/planetcards-univers-naissance-ambiance-bebe.jpg","image_width":50,"desktop_height":"natural","mobile_height":"natural","desktop_image_alignment":"left","mobile_image_alignment":"top","heading":"","heading_alignment":"center","heading_weight":500,"subheading":"<h1><strong>Naissance<\/strong><\/h1><p>Que ce soit une petite fille, un garçon ou des jumeaux, nous avons pensé à tout ! Choisissez parmi différents formats et styles, imprimé sur papier recyclé, texturé ou encore magnétique.Annoncez l’arrivée de bébé avec style en coordonnant vos faire-part de naissance, cartes de remerciement et étiquettes pour décorer vos enveloppes. <\/p><p><\/p>{{ collection.metafields.custom.description_boutique | metafield_tag }}<p><\/p><p><\/p>","text_alignment":"center","button_label":"Button","button_link":"","button_style":"primary","button_2_label":"Button","button_2_link":"","button_2_style":"primary","button_3_label":"Button","button_3_link":"","button_3_style":"primary","border_radius":false,"text_background":"#ffffff","full_width":true}},"6360f2c9-8134-4810-bd17-f4cb032a20cd":{"type":"dynamic-collection-list","blocks":{"template--21382342246697__6360f2c9-8134-4810-bd17-f4cb032a20cd-collection-1":{"type":"collection","settings":{"collection":"faire-part-naissance","image":"shopify:\/\/shop_images\/planetcards-univers-naissance-faire-part-bebe.jpg","title":"Faire-part naissance","title_heading":"span","filter":""}},"template--21382342246697__6360f2c9-8134-4810-bd17-f4cb032a20cd-collection-2":{"type":"collection","settings":{"collection":"carte-remerciement-naissance","image":"shopify:\/\/shop_images\/planetcards-univers-naissance-remerciements-bebe.jpg","title":"Carte de remerciement de naissance","title_heading":"span","filter":""}},"template--21382342246697__6360f2c9-8134-4810-bd17-f4cb032a20cd-collection-3":{"type":"collection","settings":{"collection":"creations-libres","image":"shopify:\/\/shop_images\/planetcards-univers-naissance-carte-blanche-bebe.jpg","title":"Créez votre propre design","title_heading":"span","filter":""}}},"block_order":["template--21382342246697__6360f2c9-8134-4810-bd17-f4cb032a20cd-collection-1","template--21382342246697__6360f2c9-8134-4810-bd17-f4cb032a20cd-collection-2","template--21382342246697__6360f2c9-8134-4810-bd17-f4cb032a20cd-collection-3"],"settings":{"title":"","thumbnail_columns_desktop":3,"thumbnail_columns_mobile":1,"languages_to_exclude":"","image-crop":"original","cta_label":"","cta_link":"","cta_button_style":"primary"}},"0c86a695-95e6-4385-a37f-a435d1ac8580":{"type":"dynamic-html","disabled":true,"custom_css":["p {text-align: center; font-size: 35px;}","section {margin-bottom: 0 !important;}"],"settings":{"title":"","custom_html":"<p>Nos univers<img p=\"\"><\/p>"}},"3e922343-a69d-47de-8599-41ecbe1692cd":{"type":"dynamic-collection-list","blocks":{"template--21382342246697__3e922343-a69d-47de-8599-41ecbe1692cd-collection-1":{"type":"collection","settings":{"collection":"faire-part-naissance","title":"Fille","title_heading":"span","filter":""}},"template--21382342246697__3e922343-a69d-47de-8599-41ecbe1692cd-collection-2":{"type":"collection","settings":{"collection":"faire-part-naissance","title":"Garçon","title_heading":"span","filter":""}},"template--21382342246697__3e922343-a69d-47de-8599-41ecbe1692cd-collection-3":{"type":"collection","settings":{"collection":"faire-part-naissance","title":"Original","title_heading":"span","filter":""}},"template--21382342246697__3e922343-a69d-47de-8599-41ecbe1692cd-collection-4":{"type":"collection","settings":{"collection":"faire-part-naissance","image":"shopify:\/\/shop_images\/planetcards-univers-naissance-ficelle-bebe.jpg","title":"Ficelles","title_heading":"span","filter":""}},"template--21382342246697__3e922343-a69d-47de-8599-41ecbe1692cd-collection-5":{"type":"collection","settings":{"collection":"faire-part-naissance","image":"shopify:\/\/shop_images\/planetcards-univers-naissance-faire-part-marque-page.jpg","title":"Marque-page","title_heading":"span","filter":""}},"70ead132-1968-41c2-b92d-7bf0fccc1040":{"type":"collection","settings":{"collection":"faire-part-naissance","title":"Animaux","title_heading":"span","filter":""}}},"block_order":["template--21382342246697__3e922343-a69d-47de-8599-41ecbe1692cd-collection-1","template--21382342246697__3e922343-a69d-47de-8599-41ecbe1692cd-collection-2","template--21382342246697__3e922343-a69d-47de-8599-41ecbe1692cd-collection-3","template--21382342246697__3e922343-a69d-47de-8599-41ecbe1692cd-collection-4","template--21382342246697__3e922343-a69d-47de-8599-41ecbe1692cd-collection-5","70ead132-1968-41c2-b92d-7bf0fccc1040"],"custom_css":[],"settings":{"title":"","thumbnail_columns_desktop":6,"thumbnail_columns_mobile":2,"languages_to_exclude":"","image-crop":"circle","cta_label":"","cta_link":"","cta_button_style":"primary"}},"0d52cf06-a07b-4b83-91e4-315b6a82b2db":{"type":"dynamic-image-with-text","settings":{"section_heading":"","image":"shopify:\/\/shop_images\/planetcards-univers-naissance-faire-part-magnet-bebe.jpg","image_width":50,"desktop_height":"natural","mobile_height":"natural","desktop_image_alignment":"right","mobile_image_alignment":"top","heading":"Faire-part magnétiques","heading_alignment":"left","heading_size":35,"heading_weight":501,"subheading":"<p>Votre Smartphone déborde de photos de Bébé ? Donnez-leur l'écrin qu'elles méritent en les imprimant dans un bel album photo que vous aurez plaisir à feuilleter ensemble dans quelques années.<\/p>","text_alignment":"left","button_label":"Y clique ici","button_link":"","button_style":"primary","button_2_label":"Button","button_2_link":"","button_2_style":"primary","button_3_label":"y clique ici","button_3_link":"shopify:\/\/collections\/faire-part-naissance-magnet","button_3_style":"primary","border_radius":false,"text_background":"#ffffff","full_width":false}},"9da7e9b6-ebf9-4797-9fc4-fd37c73ea7f1":{"type":"dynamic-html","custom_css":["p {text-align: center; font-size: 30px;}","section {margin-bottom: 0 !important;}"],"settings":{"title":"","custom_html":"<p>Découvrez nos dernières cré<img style=\"margin:0\" src=\"https:\/\/cdn.shopify.com\/s\/files\/1\/0799\/1656\/4777\/files\/logo-heart.svg?v=1692868355\">tions<\/p>"}},"8cbf4db0-3996-4a08-ba17-06154dfe2461":{"type":"dynamic-featured-collection","blocks":{"837dee31-9010-4602-8dae-0b3bfa017fb5":{"type":"title_card","settings":{"horizontal_size":"1","vertical_size":"1","text_alignment":"bottom-right","pre_heading":"","heading":"","text_color":"#ffffff","cta_label":"Nos Faire-parts","overlay_color":"#4d4d4d","overlay_opacity":14}}},"block_order":["837dee31-9010-4602-8dae-0b3bfa017fb5"],"settings":{"title":"","layout":"grid","collection":"faire-part-naissance","product_count":4,"cta_label":"","cta_button_style":"primary"}},"b3601cec-f33b-44cd-bbfa-1227195c94d3":{"type":"dynamic-featured-collection","blocks":{"8b1ebfb9-1503-4bd1-afba-b4f474ce41e4":{"type":"title_card","settings":{"horizontal_size":"2","vertical_size":"2","text_alignment":"center-center","pre_heading":"Nos","heading":"Remerciements","text_color":"#ffffff","cta_label":"See more","overlay_color":"#000000","overlay_opacity":50}}},"block_order":["8b1ebfb9-1503-4bd1-afba-b4f474ce41e4"],"settings":{"title":"","layout":"slideshow","collection":"remerciement-naissance-magnet","product_count":4,"cta_label":"","cta_button_style":"primary"}},"361f22c1-eb45-464b-b359-dbd1b718e902":{"type":"dynamic-rich-text","custom_css":["h1 {font-size: 35px;}","p {text-align: center; font-size: 15px;}","section {margin-bottom: 0 !important;}"],"settings":{"width":"full-width","title":"","richtitle":"<h1>Créez une chambre <em>unique <\/em>pour votre enfant<\/h1>","text":"<p>Choisissez une jolie toise ou une affiche personnalisée assortie <br\/>à son faire-part de naissance ou à la décoration de sa chambre.<\/p>","heading_size":"medium","text_alignment":"center","is_title":false,"languages_to_exclude":""}},"9f4690f3-9165-4973-a4d5-6044dc82cf70":{"type":"dynamic-shoppable-image","blocks":{"template--21382342246697__9f4690f3-9165-4973-a4d5-6044dc82cf70-hotspot-1":{"type":"hotspot","disabled":true,"settings":{"product":"","x_axis_number":"10","y_axis_number":"65"}},"template--21382342246697__9f4690f3-9165-4973-a4d5-6044dc82cf70-hotspot-2":{"type":"hotspot","settings":{"product":"arc-en-ciel-30x30","x_axis_number":"38","y_axis_number":"50"}},"template--21382342246697__9f4690f3-9165-4973-a4d5-6044dc82cf70-hotspot-3":{"type":"hotspot","settings":{"product":"savane","x_axis_number":"49","y_axis_number":"55"}}},"block_order":["template--21382342246697__9f4690f3-9165-4973-a4d5-6044dc82cf70-hotspot-1","template--21382342246697__9f4690f3-9165-4973-a4d5-6044dc82cf70-hotspot-2","template--21382342246697__9f4690f3-9165-4973-a4d5-6044dc82cf70-hotspot-3"],"disabled":true,"settings":{"title":"","image":"shopify:\/\/shop_images\/planetcards-univers-naissance-affiches-toises-bebe.jpg","image_width":"full","link_text":"View product","textbox_title":"","textbox_subheading":"","textbox_button_label":"","textbox_button_link":"","textbox_button_style":"primary","textbox_text_alignment":"left","textbox_text_position":"right","title_heading":"h2"}},"98594fcb-cbc5-41ea-bd3d-18bb9713706c":{"type":"dynamic-rich-text","disabled":true,"custom_css":["p {font-size: 35px;}"],"settings":{"width":"full-width","title":"","richtitle":"<p>Marquez les esprits avec nos <em>designs originaux<\/em><\/p>","text":"","heading_size":"medium","text_alignment":"center","is_title":false,"languages_to_exclude":""}},"26d1f78d-0536-4fa1-89f4-3ffcb9097937":{"type":"dynamic-promo-grid","blocks":{"template--21382342246697__26d1f78d-0536-4fa1-89f4-3ffcb9097937-promotion-1":{"type":"promotion","settings":{"title":"Affiches Naissance","text":"","color":"#4d4d4d","block_link":"","button_text":"Affiche","button_style":"primary","show_overlay":false,"background":"","opacity":50}},"template--21382342246697__26d1f78d-0536-4fa1-89f4-3ffcb9097937-promotion-2":{"type":"promotion","settings":{"title":"Toises","text":"","color":"#4d4d4d","block_link":"","button_text":"","button_style":"primary","show_overlay":false,"background":"","opacity":50}}},"block_order":["template--21382342246697__26d1f78d-0536-4fa1-89f4-3ffcb9097937-promotion-1","template--21382342246697__26d1f78d-0536-4fa1-89f4-3ffcb9097937-promotion-2"],"settings":{"title":"","section_height":"small","section_columns":2,"text_alignment":"top-left"}},"b67f253f-96d8-46fe-9f6e-5a81ee318738":{"type":"dynamic-promo-grid","blocks":{"template--21382342246697__b67f253f-96d8-46fe-9f6e-5a81ee318738-promotion-1":{"type":"promotion","settings":{"image":"shopify:\/\/shop_images\/planetcards-univers-naissance-ficelle-bebe.jpg","title":"","text":"","color":"#4d4d4d","block_link":"https:\/\/planet-cards-store.myshopify.com\/collections\/faire-part-naissance-1?filter.p.m.custom.languages=fr&filter.v.option.format=Paysage+Portefeuille+%2B+Ficelle+15%2C1+x+10%2C8+cm&filter.v.option.format=Carr%C3%A9+Pli%C3%A9+%2B+Ficelle+14+x+14+cm","button_text":"Faire-part avec ficelle","button_style":"secondary","show_overlay":false,"background":"","opacity":50}},"template--21382342246697__b67f253f-96d8-46fe-9f6e-5a81ee318738-promotion-2":{"type":"promotion","settings":{"image":"shopify:\/\/shop_images\/planetcards-univers-naissance-faire-part-magnet-bebe.jpg","title":"","text":"","color":"#4d4d4d","block_link":"https:\/\/planet-cards-store.myshopify.com\/collections\/faire-part-naissance-1?filter.p.m.custom.languages=fr&filter.v.option.format=Carr%C3%A9+Pli%C3%A9+%2B+Ficelle+14+x+14+cm&filter.v.option.format=Paysage+Portefeuille+%2B+Ficelle+15%2C1+x+10%2C8+cm","button_text":"Faire-part magnétique","button_style":"secondary","show_overlay":false,"background":"","opacity":1}},"template--21382342246697__b67f253f-96d8-46fe-9f6e-5a81ee318738-promotion-3":{"type":"promotion","settings":{"image":"shopify:\/\/shop_images\/planetcards-univers-naissance-faire-part-marque-page.jpg","title":"","text":"","color":"#4d4d4d","block_link":"https:\/\/planet-cards-store.myshopify.com\/collections\/faire-part-naissance-1?filter.p.m.custom.languages=fr&filter.v.option.format=Marque+Page+Recto+Verso+5%2C5+x+18%2C2+cm","button_text":"Faire-part marque-page","button_style":"secondary","show_overlay":false,"background":"","opacity":50}}},"block_order":["template--21382342246697__b67f253f-96d8-46fe-9f6e-5a81ee318738-promotion-1","template--21382342246697__b67f253f-96d8-46fe-9f6e-5a81ee318738-promotion-2","template--21382342246697__b67f253f-96d8-46fe-9f6e-5a81ee318738-promotion-3"],"disabled":true,"settings":{"title":"","section_height":"small","section_columns":3,"text_alignment":"top-left"}},"1c5c7690-b411-4309-9b6d-dcb04d0ca102":{"type":"dynamic-rich-text","custom_css":["h1 {font-size: 35px;}","p {text-align: center; font-size: 35px;}","section {margin-bottom: 0 !important;}"],"settings":{"width":"full-width","title":"","richtitle":"<p>Racontez, <em>l'histoire de ses premiers mois <\/em>en photo !<\/p>","text":"","heading_size":"medium","text_alignment":"center","is_title":false,"languages_to_exclude":""}},"9b127f90-ca68-4ae3-955e-ca979b134256":{"type":"dynamic-image-with-text","settings":{"section_heading":"","image":"shopify:\/\/shop_images\/planetcards-univers-naissance-livre-photo-personnalise-bebe.jpg","image_width":50,"desktop_height":"natural","mobile_height":"natural","desktop_image_alignment":"left","mobile_image_alignment":"top","heading":"Album photo bébé","heading_alignment":"left","heading_size":35,"heading_weight":501,"subheading":"<p>Votre Smartphone déborde de photos de Bébé ? Donnez-leur l'écrin qu'elles méritent en les imprimant dans un bel album photo que vous aurez plaisir à feuilleter ensemble dans quelques années.<\/p>","text_alignment":"left","button_label":"Button","button_link":"","button_style":"primary","button_2_label":"Je créé mon album","button_2_link":"shopify:\/\/collections\/album-photo","button_2_style":"primary","button_3_label":"Button","button_3_link":"","button_3_style":"primary","border_radius":false,"text_background":"#ffffff","full_width":false}},"979dc365-51f1-4885-a12f-06d443714e6e":{"type":"dynamic-blog-posts","disabled":true,"custom_css":[".home-section--text p {font-size: 35px;}"],"settings":{"title":"","text":"<p>Nos <em>derniers <\/em>articles<\/p>","blog":"","show_date":true,"show_author":true,"show_excerpt":true}},"6023e948-f382-4e83-8686-20f05fdf6465":{"type":"dynamic-html","custom_css":["h2 {font-size: 18px; font-weight: bold;}","h3 {font-size: 15px; font-weight: bold;}","h4 {font-size: 14px; font-weight: italic;}","p {font-size: 13px;}","ul {font-size: 13px; font-weight: italic;}"],"settings":{"title":"","custom_html":"<p>La naissance d'un enfant est un moment exceptionnel ! Notre carterie de naissance est là pour vous accompagner dans cet événement familial incontournable, <strong>des faire parts de naissance, des cartes de remerciements , des étiquettes pour décorer vos enveloppes.<\/strong> Tout pour rendre cette naissance encore plus belle.<\/p>\n\n\n\n\n<p>Félicitations aux nouveaux parents ! Bébé est enfin parmi nous et vous songez déjà à annoncer cet heureux évènement au plus grand nombre. Que vous souhaitiez annoncer l’arrivée de bébé ou bien si vous avez envie de remercier vos proches pour leurs délicates attentions au cours des derniers mois de votre grossesse, Planet Cards vous offre la possibilité de choisir parmi une large gamme de cartes de naissance qui vous séduiront à coup sûr. <strong>Tous nos modèles sont entièrement personnalisables<\/strong>, ce qui vous permet de créer une carterie pour célébrer la naissance de votre fille, garçon, jumeaux ou triplets à votre image !<\/p>\n\n<h2>Comment choisir le design idéal de vos faire part après la naissance de votre enfant ?<\/h2>\n\n<p><strong>La meilleure façon de présenter votre bébé à vos proches est au travers d’un joli faire part. <\/strong>Nul doute qu’un faire part naissance de Planet Cards saura exprimer votre immense joie !\nEn effet, notre équipe de graphistes est en constante création de plus beaux modèles pour satisfaire le plus grand nombre. Vous devez d’abord choisir le modèle qu’il vous faut, <strong>vous avez l’embarras du choix !<\/strong> Nous vous proposons une large gamme de modèles, allant du plus classique au plus original, en passant par des faire part créatifs et sobres. À continuation quelques étapes à suivre :<\/p>\n\n<h3>Choisissez votre modèle préféré<\/h3>\n\n<p>Qu’il s’agisse d’une carte de naissance pour petite fille ou petit garçon vous avez une multitude de designs adaptés à toute type de naissance sur notre site, tous aussi craquants les uns que les autres.\nLes thématiques les plus populaires :\n\n<\/p><ul>\n  <li>\n<strong>Façon humoristique<\/strong>, adaptée aux parents qui souhaitent sortir du lot !<\/li>\n  <li>\n<strong>Style champêtre<\/strong> pour les parents adeptes de la verdure ! Vous trouverez ici le faire part naissance façon aquarelle pour un rendu plus artistique<\/li>\n  <li>\n<strong>Thématique classique illustrée<\/strong> avec les indémodables petits animaux tous mignons : lapins, papillons et nounours !<\/li>\n  <li>Les modèles de faire-part naissance créatifs <strong>à personnaliser de A à Z<\/strong> par vos soins. Vous avez plusieurs formats disponibles pour exprimer tout votre talent !<\/li>\n<\/ul>\n\n<p>Une fois votre perle rare trouvée, c’est facile ! Vous n’avez plus qu’à <strong>choisir le papier, la couleur et le format adapté à votre faire part naissance.<\/strong> Vous pouvez y ajouter également la photo de bébé dessus, ce sera une raison de plus pour que les destinataires, grands-parents, amis et collègues, l’affichent fièrement sur leurs meubles et frigo.\n\n\nVous avez vu, le tout se réalise en ligne. Ca s'appelle la magie de la personnalisation en ligne. Nous avons conçu un outil de personnalisation facile et intuitif d’usage pour que la création de toute votre carterie de naissance soit à la portée de tous. Il ne vous reste plus qu’à tester l’outil et à personnaliser de toute pièce le faire part de vos rêves. L’impression et la fabrication sont notre affaire.<\/p>\n\n<h3>Personnalisez en ligne votre carte en quelques clics<\/h3>\n\n<p>Si vous envoyez un faire-part de naissance, <strong>n’oubliez pas de le personnaliser pour lui donner une touche originale.<\/strong> A vous donc de choisir la meilleure photo possible pour rendre votre création unique en son genre. Ainsi, choisir un portrait de votre bébé sera encore plus mignon et adorable lorsque vos proches ouvriront l’enveloppe pour découvrir sa jolie petite bouille. Vous pouvez aussi opter pour une photo avec une touche de mystère sur laquelle on ne voit que les mains des parents et celles du nouveau né. Cela donnera encore plus envie à votre entourage de venir découvrir le visage de bébé.\n\n\nNotre outil de personnalisation en ligne, vous permet facilement de personnaliser vos faire-part et satisfaire toutes vos envies. Choisissez vos teintes, vos formats préférés et papiers parmi une ample sélection. Vous pouvez placer facilement vos textes sur le recto verso de votre correspondance. En seulement quelques clics vous obtiendrez la carte qui mettra le plus en valeur votre bout de chou.<\/p>\n\n<h2>Partagez votre nouvelle vie en envoyant une carte de remerciements naissance à vos proches<\/h2>\n\n<h3>Des designs généreux pour dire merci à votre entourage<\/h3>\n\n<p>Si vous souhaitez remercier vos proches et montrer à quel point vous êtes heureux de les avoir auprès de vous pendant une période aussi importante, Planet Cards vous conseille vivement de choisir une carte de remerciements naissance parmi tous les designs disponibles.<\/p>\n\n<h3>Dites merci à vos proches en personnalisant une carte pliée ou tout autre format original choisi en amont.<\/h3>\n\n<p><strong>Nos graphistes sont sans cesse à l'affût des nouvelles tendances et vous concoctent de nouveaux designs pour plaire au plus grand nombre.<\/strong> Vous trouverez sur notre site de beaux modèles à des prix très intéressants pour une impression de qualité. Il ne vous reste plus qu’à trouver le thème idéal pour remercier de la façon la plus jolie qu’il soit en créant une carte en adéquation avec votre imagination, et le tour est joué !<\/p>\n\n<h3>Des remerciements naissance à personnaliser facilement en ligne<\/h3>\n\n<p>Une carte de remerciements que vous personnalisez sera le parfait cadeau pour ceux qui vous ont soutenu pendant la grossesse et qui comptent dans votre vie. Si vous gardez en tête le fait de vouloir leur faire plaisir, nul doute que votre création sera un souvenir adorable pour vos amis et votre famille. En plus d’être une attention très appréciée, ce sera un élément idéal pour décorer un mur, un meuble ou un frigo. Une de nos options permettra d’en faire une carte aimantée par exemple, qui pourra servir de faire part de naissance magnet . Il est aussi conseillé aux proches qui reçoivent ce type de souvenir de l’encadrer s’il s’agit d’un format recto avec un portrait du bébé, ou bien de le poser sur un meuble dans son salon si c’est une carte pliée. <\/p>\n\n<h3>Des cartes comme témoignage de reconnaissance oui ! Mais avec du style !<\/h3>\n\n<p>La carte de remerciement de naissance délivre un message sincère à vos familles et amis. Nous sommes là pour vous aiguiller en matière de thèmes, de couleurs et graphismes exclusifs, mais seule votre imagination et les mots que vous emploierez sauront toucher le coeur de vos proches. Personnalisez donc vos remerciements en y mettant les mots qui vous viennent en tête et en choisissant la police idéale, les couleurs qui vous plaisent et la ou les photos qui iront de pair avec le design choisi.<\/p>\n\n<p><\/p>\n<h2>Customisez vos enveloppes avec des étiquettes personnalisées<\/h2>\n\n<p>Notre outil de personnalisation vous permet d’aller très loin dans la création. En effet, une fois le design choisi, il existe beaucoup d’options possibles grâce aux multiples choix esthétiques que nous vous proposons. Au même titre que vous pouvez très vite opter pour :\n\n<\/p>\n<ul>\n  <li>Des angles arrondis ou pointus\n  <\/li>\n<li>Un papier de qualité supérieure<\/li>\n  <li>Des effets 3D<\/li>\n<\/ul>\n\n<p><strong>Le graphisme même de la carte peut être retouché jusqu’aux moindres détails.<\/strong>\nCe sont tous ces petits détails qui vont contribuer à créer un effet de surprise, amener de la cohérence esthétique et faire sourire les personnes à qui vous enverrez votre carte.\n<\/p>\n\n<p>Par exemple, il vous est possible de personnaliser l’enveloppe dans laquelle se trouve le chef d’oeuvre. En plus des différentes couleurs qui vous sont proposées, nous vous conseillons de créer vos propres étiquettes naissance pour rendre les cartes et remerciements encore plus personnels. En faisant cela, vous appuierez sur un détail très important qui surprendra forcément vos proches.<\/p>\n\n\n<p>En effet, il est évident qu’envoyer un faire-part de naissance personnalisé ou une carte de remerciements unique en son genre fera plaisir à votre famille ainsi qu’à vos amis. Non seulement cela vous permet de marquer les esprits puisque vous y aurez mis tout votre coeur, mais c’est aussi une surprise visuelle qui fait office de mise en bouche. Lorsqu’un membre de votre famille va découvrir la carte avec une photo du bébé, il est évident qu’il aura très envie de vite venir vous féliciter en personne. Qu’il s’agisse d’une invitation ou d’une annonce, nous sommes certains que l’énergie créative dont vous aurez fait preuve se ressentira en découvrant la carte.<\/p>"}},"328e9f6f-94dd-4504-992a-9b130bcf3571":{"type":"dynamic-blog-posts","settings":{"title":"Lorem","text":"<p>Lorem ipsum<\/p>","blog":"naissance","show_date":true,"show_author":true,"show_excerpt":true}}},"order":["cd3dffdd-4f31-48e4-ac68-b329003b6168","6360f2c9-8134-4810-bd17-f4cb032a20cd","0c86a695-95e6-4385-a37f-a435d1ac8580","3e922343-a69d-47de-8599-41ecbe1692cd","0d52cf06-a07b-4b83-91e4-315b6a82b2db","9da7e9b6-ebf9-4797-9fc4-fd37c73ea7f1","8cbf4db0-3996-4a08-ba17-06154dfe2461","b3601cec-f33b-44cd-bbfa-1227195c94d3","361f22c1-eb45-464b-b359-dbd1b718e902","9f4690f3-9165-4973-a4d5-6044dc82cf70","98594fcb-cbc5-41ea-bd3d-18bb9713706c","26d1f78d-0536-4fa1-89f4-3ffcb9097937","b67f253f-96d8-46fe-9f6e-5a81ee318738","1c5c7690-b411-4309-9b6d-dcb04d0ca102","9b127f90-ca68-4ae3-955e-ca979b134256","979dc365-51f1-4885-a12f-06d443714e6e","6023e948-f382-4e83-8686-20f05fdf6465","328e9f6f-94dd-4504-992a-9b130bcf3571"]}